airflow_ai_sdk/__init__.py
airflow_ai_sdk/airflow.py
airflow_ai_sdk/decorators/agent.py
airflow_ai_sdk/decorators/branch.py
airflow_ai_sdk/decorators/embed.py
airflow_ai_sdk/decorators/llm.py
airflow_ai_sdk/models/base.py
airflow_ai_sdk/models/tool.py
airflow_ai_sdk/operators/agent.py
airflow_ai_sdk/operators/embed.py
airflow_ai_sdk/operators/llm.py
airflow_ai_sdk/operators/llm_branch.py
airflow_ai_sdk-0.1.6.dist-info/METADATA
airflow_ai_sdk-0.1.6.dist-info/WHEEL
airflow_ai_sdk-0.1.6.dist-info/entry_points.txt
airflow_ai_sdk-0.1.6.dist-info/licenses/LICENSE
airflow_ai_sdk-0.1.6.dist-info/RECORD
