Metadata-Version: 2.4
Name: airflow-ai-sdk
Version: 0.1.6
Summary: SDK for building LLM workflows and agents using Apache Airflow
License-File: LICENSE
Classifier: Development Status :: 4 - Beta
Classifier: Framework :: Apache Airflow
Classifier: Framework :: Apache Airflow :: Provider
Classifier: Intended Audience :: Developers
Classifier: License :: OSI Approved :: Apache Software License
Classifier: Operating System :: OS Independent
Classifier: Programming Language :: Python
Classifier: Programming Language :: Python :: 3
Classifier: Programming Language :: Python :: 3.10
Classifier: Programming Language :: Python :: 3.11
Classifier: Programming Language :: Python :: 3.12
Requires-Python: >=3.10
Requires-Dist: apache-airflow>=2.7.0
Requires-Dist: pydantic-ai-slim>=0.4.0
Requires-Dist: typing-extensions>=4.0.0
Provides-Extra: anthropic
Requires-Dist: pydantic-ai-slim[anthropic]>=0.4.0; extra == 'anthropic'
Provides-Extra: bedrock
Requires-Dist: pydantic-ai-slim[bedrock]>=0.4.0; extra == 'bedrock'
Provides-Extra: cohere
Requires-Dist: pydantic-ai-slim[cohere]>=0.4.0; extra == 'cohere'
Provides-Extra: duckduckgo
Requires-Dist: pydantic-ai-slim[duckduckgo]>=0.4.0; extra == 'duckduckgo'
Provides-Extra: groq
Requires-Dist: pydantic-ai-slim[groq]>=0.4.0; extra == 'groq'
Provides-Extra: mcp
Requires-Dist: pydantic-ai-slim[mcp]>=0.4.0; extra == 'mcp'
Provides-Extra: mistral
Requires-Dist: pydantic-ai-slim[mistral]>=0.4.0; extra == 'mistral'
Provides-Extra: openai
Requires-Dist: pydantic-ai-slim[openai]>=0.4.0; extra == 'openai'
Provides-Extra: vertexai
Requires-Dist: pydantic-ai-slim[vertexai]>=0.4.0; extra == 'vertexai'
